[{"model": "admin.logentry", "pk": 1, "fields": {"action_time": "2025-04-15T09:20:32.235Z", "user": 1, "content_type": 7, "object_id": "0", "object_repr": "Janvier", "action_flag": 1, "change_message": "[{\"added\": {}}]"}}, {"model": "admin.logentry", "pk": 2, "fields": {"action_time": "2025-04-15T09:20:54.941Z", "user": 1, "content_type": 7, "object_id": "1", "object_repr": "Février", "action_flag": 1, "change_message": "[{\"added\": {}}]"}}, {"model": "admin.logentry", "pk": 3, "fields": {"action_time": "2025-04-15T09:20:59.747Z", "user": 1, "content_type": 7, "object_id": "2", "object_repr": "Mars", "action_flag": 1, "change_message": "[{\"added\": {}}]"}}, {"model": "admin.logentry", "pk": 4, "fields": {"action_time": "2025-04-15T09:21:05.115Z", "user": 1, "content_type": 7, "object_id": "3", "object_repr": "Avril", "action_flag": 1, "change_message": "[{\"added\": {}}]"}}, {"model": "admin.logentry", "pk": 5, "fields": {"action_time": "2025-04-15T09:21:09.801Z", "user": 1, "content_type": 7, "object_id": "4", "object_repr": "Mai", "action_flag": 1, "change_message": "[{\"added\": {}}]"}}, {"model": "admin.logentry", "pk": 6, "fields": {"action_time": "2025-04-15T09:21:22.396Z", "user": 1, "content_type": 7, "object_id": "5", "object_repr": "Juin", "action_flag": 1, "change_message": "[{\"added\": {}}]"}}, {"model": "admin.logentry", "pk": 7, "fields": {"action_time": "2025-04-15T09:21:27.756Z", "user": 1, "content_type": 7, "object_id": "6", "object_repr": "Juillet", "action_flag": 1, "change_message": "[{\"added\": {}}]"}}, {"model": "admin.logentry", "pk": 8, "fields": {"action_time": "2025-04-15T09:21:41.582Z", "user": 1, "content_type": 7, "object_id": "7", "object_repr": "Août", "action_flag": 1, "change_message": "[{\"added\": {}}]"}}, {"model": "admin.logentry", "pk": 9, "fields": {"action_time": "2025-04-15T09:21:48.188Z", "user": 1, "content_type": 7, "object_id": "8", "object_repr": "Septembre", "action_flag": 1, "change_message": "[{\"added\": {}}]"}}, {"model": "admin.logentry", "pk": 10, "fields": {"action_time": "2025-04-15T09:22:01.987Z", "user": 1, "content_type": 7, "object_id": "9", "object_repr": "Octobre", "action_flag": 1, "change_message": "[{\"added\": {}}]"}}, {"model": "admin.logentry", "pk": 11, "fields": {"action_time": "2025-04-15T09:22:10.862Z", "user": 1, "content_type": 7, "object_id": "10", "object_repr": "Novembre", "action_flag": 1, "change_message": "[{\"added\": {}}]"}}, {"model": "admin.logentry", "pk": 12, "fields": {"action_time": "2025-04-15T09:22:24.883Z", "user": 1, "content_type": 7, "object_id": "11", "object_repr": "Décembre", "action_flag": 1, "change_message": "[{\"added\": {}}]"}}, {"model": "auth.permission", "pk": 1, "fields": {"name": "Can add log entry", "content_type": 1, "codename": "add_logentry"}}, {"model": "auth.permission", "pk": 2, "fields": {"name": "Can change log entry", "content_type": 1, "codename": "change_logentry"}}, {"model": "auth.permission", "pk": 3, "fields": {"name": "Can delete log entry", "content_type": 1, "codename": "delete_logentry"}}, {"model": "auth.permission", "pk": 4, "fields": {"name": "Can view log entry", "content_type": 1, "codename": "view_logentry"}}, {"model": "auth.permission", "pk": 5, "fields": {"name": "Can add permission", "content_type": 2, "codename": "add_permission"}}, {"model": "auth.permission", "pk": 6, "fields": {"name": "Can change permission", "content_type": 2, "codename": "change_permission"}}, {"model": "auth.permission", "pk": 7, "fields": {"name": "Can delete permission", "content_type": 2, "codename": "delete_permission"}}, {"model": "auth.permission", "pk": 8, "fields": {"name": "Can view permission", "content_type": 2, "codename": "view_permission"}}, {"model": "auth.permission", "pk": 9, "fields": {"name": "Can add group", "content_type": 3, "codename": "add_group"}}, {"model": "auth.permission", "pk": 10, "fields": {"name": "Can change group", "content_type": 3, "codename": "change_group"}}, {"model": "auth.permission", "pk": 11, "fields": {"name": "Can delete group", "content_type": 3, "codename": "delete_group"}}, {"model": "auth.permission", "pk": 12, "fields": {"name": "Can view group", "content_type": 3, "codename": "view_group"}}, {"model": "auth.permission", "pk": 13, "fields": {"name": "Can add user", "content_type": 4, "codename": "add_user"}}, {"model": "auth.permission", "pk": 14, "fields": {"name": "Can change user", "content_type": 4, "codename": "change_user"}}, {"model": "auth.permission", "pk": 15, "fields": {"name": "Can delete user", "content_type": 4, "codename": "delete_user"}}, {"model": "auth.permission", "pk": 16, "fields": {"name": "Can view user", "content_type": 4, "codename": "view_user"}}, {"model": "auth.permission", "pk": 17, "fields": {"name": "Can add content type", "content_type": 5, "codename": "add_contenttype"}}, {"model": "auth.permission", "pk": 18, "fields": {"name": "Can change content type", "content_type": 5, "codename": "change_contenttype"}}, {"model": "auth.permission", "pk": 19, "fields": {"name": "Can delete content type", "content_type": 5, "codename": "delete_contenttype"}}, {"model": "auth.permission", "pk": 20, "fields": {"name": "Can view content type", "content_type": 5, "codename": "view_contenttype"}}, {"model": "auth.permission", "pk": 21, "fields": {"name": "Can add session", "content_type": 6, "codename": "add_session"}}, {"model": "auth.permission", "pk": 22, "fields": {"name": "Can change session", "content_type": 6, "codename": "change_session"}}, {"model": "auth.permission", "pk": 23, "fields": {"name": "Can delete session", "content_type": 6, "codename": "delete_session"}}, {"model": "auth.permission", "pk": 24, "fields": {"name": "Can view session", "content_type": 6, "codename": "view_session"}}, {"model": "auth.permission", "pk": 25, "fields": {"name": "Can add month model", "content_type": 7, "codename": "add_monthmodel"}}, {"model": "auth.permission", "pk": 26, "fields": {"name": "Can change month model", "content_type": 7, "codename": "change_monthmodel"}}, {"model": "auth.permission", "pk": 27, "fields": {"name": "Can delete month model", "content_type": 7, "codename": "delete_monthmodel"}}, {"model": "auth.permission", "pk": 28, "fields": {"name": "Can view month model", "content_type": 7, "codename": "view_monthmodel"}}, {"model": "auth.user", "pk": 1, "fields": {"password": "pbkdf2_sha256$1000000$RZcJ7d759STXDk1tyepPfh$fPy8D5tnsJ+03oHrswcnaB0OYEhoWEFT7KMKnyo0oB8=", "last_login": "2025-04-15T09:18:51.521Z", "is_superuser": true, "username": "tnicolau", "first_name": "", "last_name": "", "email": "", "is_staff": true, "is_active": true, "date_joined": "2025-04-15T09:17:53.359Z", "groups": [], "user_permissions": []}}, {"model": "contenttypes.contenttype", "pk": 1, "fields": {"app_label": "admin", "model": "logentry"}}, {"model": "contenttypes.contenttype", "pk": 2, "fields": {"app_label": "auth", "model": "permission"}}, {"model": "contenttypes.contenttype", "pk": 3, "fields": {"app_label": "auth", "model": "group"}}, {"model": "contenttypes.contenttype", "pk": 4, "fields": {"app_label": "auth", "model": "user"}}, {"model": "contenttypes.contenttype", "pk": 5, "fields": {"app_label": "contenttypes", "model": "contenttype"}}, {"model": "contenttypes.contenttype", "pk": 6, "fields": {"app_label": "sessions", "model": "session"}}, {"model": "contenttypes.contenttype", "pk": 7, "fields": {"app_label": "api", "model": "monthmodel"}}, {"model": "sessions.session", "pk": "1c80horuqvbwwruvfdvl0hoageiqhbdp", "fields": {"session_data": ".eJxVjMEOwiAQRP-FsyGFQikevfcbyMLuStVAUtqT8d9tkx70Npn3Zt4iwLbmsDVawoziKpS4_HYR0pPKAfAB5V5lqmVd5igPRZ60yakivW6n-3eQoeV9zQ76cbCGdURiRZ3WezZo0TO4wSmPmBL3pouuZx89joCOIYHSlgyKzxf-qjj8:1u4cRP:qxhXagHRaXbxRWZvyT5ct-Xq59rr_n73YQy9W7VJlKg", "expire_date": "2025-04-29T09:18:51.529Z"}}, {"model": "api.monthmodel", "pk": 0, "fields": {"name": "Janvier"}}, {"model": "api.monthmodel", "pk": 1, "fields": {"name": "Février"}}, {"model": "api.monthmodel", "pk": 2, "fields": {"name": "Mars"}}, {"model": "api.monthmodel", "pk": 3, "fields": {"name": "Avril"}}, {"model": "api.monthmodel", "pk": 4, "fields": {"name": "Mai"}}, {"model": "api.monthmodel", "pk": 5, "fields": {"name": "Juin"}}, {"model": "api.monthmodel", "pk": 6, "fields": {"name": "Juillet"}}, {"model": "api.monthmodel", "pk": 7, "fields": {"name": "Août"}}, {"model": "api.monthmodel", "pk": 8, "fields": {"name": "Septembre"}}, {"model": "api.monthmodel", "pk": 9, "fields": {"name": "Octobre"}}, {"model": "api.monthmodel", "pk": 10, "fields": {"name": "Novembre"}}, {"model": "api.monthmodel", "pk": 11, "fields": {"name": "Décembre"}}]